pyaudi-1.9.1.dist-info/top_level.txt
pyaudi-1.9.1.dist-info/RECORD
pyaudi-1.9.1.dist-info/METADATA
pyaudi-1.9.1.dist-info/WHEEL
pyaudi/core.so
pyaudi/_version.py
pyaudi/test.py
pyaudi/__init__.py
pyaudi/.libs/libboost_serialization-a2bbf0df.so.1.70.0
pyaudi/.libs/libmpfr-a5f70da1.so.6.0.2
pyaudi/.libs/libgmp-c0146b93.so.10.3.2
pyaudi/.libs/libobake-941a7883.so.4.0
pyaudi/.libs/libmp++-796aafdd.so.3.0
pyaudi/.libs/libtbb-bd962542.so.2
